log_call/__init__.py
log_call-0.1.0.dist-info/LICENSE
log_call-0.1.0.dist-info/METADATA
log_call-0.1.0.dist-info/WHEEL
log_call-0.1.0.dist-info/top_level.txt
log_call-0.1.0.dist-info/RECORD
