Metadata-Version: 2.1
Name: log_call
Version: 0.1.0
Summary: Library to log function or bond-method calls
Home-page: https://github.com/Agent-Hellboy/log_call
Author: Prince Roshan
Author-email: princekrroshan01@gmail.com
License: MIT
Keywords: logger,logging-tool
Classifier: Programming Language :: Python :: 3.7
Classifier: Programming Language :: Python :: 3.8
Classifier: Programming Language :: Python :: 3.9
Classifier: Programming Language :: Python :: 3.10
Classifier: Operating System :: OS Independent
Requires-Python: >=3.7
License-File: LICENSE
